{"stat.mineBlock.24":6,"stat.useItem.276":18,"stat.killEntity.Skeleton":3,"stat.mineBlock.49":1,"stat.mineBlock.48":5,"stat.walkOneCm":198916,"achievement.openInventory":133,"stat.leaveGame":1,"stat.damageTaken":39135,"stat.mineBlock.4":3,"stat.mineBlock.3":1,"stat.mineBlock.1":14,"stat.killEntity.Enderman":1,"stat.mobKills":120,"stat.killEntity.Creeper":2,"stat.flyOneCm":379170,"stat.deaths":1,"stat.mineBlock.15":7,"stat.drop":67,"stat.jump":1388,"stat.swimOneCm":1767,"stat.playOneMinute":62153,"stat.fallOneCm":78163,"stat.useItem.4":22,"stat.damageDealt":74625,"stat.killEntity.Zombie":4,"achievement.exploreAllBiomes":{"value":0,"progress":["Birch Forest Hills","ForestHills","Roofed Forest","Birch Forest","Plains","Beach","Stone Beach","Extreme Hills+","Villages","Ocean","River","Forest","Taiga","Desert","Extreme Hills","Swampland","Deep Ocean"]},"stat.mineBlock.31":43}