{"stat.useItem.276":18,"stat.mineBlock.49":1,"stat.mineBlock.48":5,"stat.walkOneCm":265508,"stat.leaveGame":3,"stat.killEntity.Creeper":3,"stat.mineBlock.15":7,"stat.mineBlock.18":4,"stat.jump":1688,"stat.swimOneCm":2289,"stat.fallOneCm":93259,"achievement.exploreAllBiomes":{"value":0,"progress":["Birch Forest Hills","ForestHills","Roofed Forest","Birch Forest","Plains","Beach","Stone Beach","Extreme Hills+","Villages","Ocean","River","Forest","Taiga","Desert","Extreme Hills","Swampland","Deep Ocean"]},"stat.mineBlock.24":6,"stat.killEntity.Skeleton":4,"achievement.openInventory":204,"stat.damageTaken":41110,"stat.mineBlock.4":3,"stat.mineBlock.3":66,"stat.mineBlock.1":14,"stat.killEntity.Enderman":1,"stat.mobKills":124,"stat.flyOneCm":425540,"stat.deaths":1,"stat.drop":81,"stat.playOneMinute":79871,"stat.killEntity.Witch":1,"stat.useItem.4":22,"stat.useItem.3":55,"stat.damageDealt":75696,"stat.killEntity.Zombie":5,"stat.mineBlock.31":43,"stat.diveOneCm":1606}